scotty/__init__.py
scotty/cli.py
scotty/log.py
scotty/version.py
scotty/cmd/__init__.py
scotty/cmd/base.py
scotty/cmd/experiment.py
scotty/cmd/resource.py
scotty/cmd/workload.py
scotty/core/__init__.py
scotty/core/checkout.py
scotty/core/components.py
scotty/core/context.py
scotty/core/exceptions.py
scotty/core/executor.py
scotty/core/moduleloader.py
scotty/core/report.py
scotty/core/settings.py
scotty/core/workspace.py
scotty/tests/__init__.py
scotty/tests/functional/__init__.py
scotty/tests/functional/test_experiment_clean.py
scotty/tests/functional/test_experiment_perform.py
scotty/tests/functional/test_experiment_perform_parallel.py
scotty/tests/unit/__init__.py
scotty/tests/unit/test_utils.py
scotty/tests/unit/core/__init__.py
scotty/tests/unit/core/test_checkout.py
scotty/tests/unit/core/test_components.py
scotty/tests/unit/core/test_executor.py
scotty/utils/__init__.py
scotty/utils/base.py
scotty/utils/experiment.py
scotty/utils/openstack.py
scotty/utils/resource.py
scotty/utils/resultstore.py
scotty/utils/workload.py
scotty/workflows/__init__.py
scotty/workflows/base.py
scotty/workflows/experiment.py
scotty/workflows/resource.py
scotty/workflows/workflows.py
scotty.py-0.8.9.data/data/etc/scotty/scotty.conf
scotty.py-0.8.9.dist-info/AUTHORS
scotty.py-0.8.9.dist-info/METADATA
scotty.py-0.8.9.dist-info/WHEEL
scotty.py-0.8.9.dist-info/entry_points.txt
scotty.py-0.8.9.dist-info/pbr.json
scotty.py-0.8.9.dist-info/top_level.txt
scotty.py-0.8.9.dist-info/RECORD
